odoo/addons/sale_product_rating_verified/README.rst
odoo/addons/sale_product_rating_verified/__init__.py
odoo/addons/sale_product_rating_verified/__manifest__.py
odoo/addons/sale_product_rating_verified/i18n/es.po
odoo/addons/sale_product_rating_verified/i18n/sale_product_rating_verified.pot
odoo/addons/sale_product_rating_verified/models/__init__.py
odoo/addons/sale_product_rating_verified/models/rating.py
odoo/addons/sale_product_rating_verified/readme/CONTRIBUTORS.rst
odoo/addons/sale_product_rating_verified/readme/DESCRIPTION.rst
odoo/addons/sale_product_rating_verified/readme/USAGE.rst
odoo/addons/sale_product_rating_verified/static/description/icon.png
odoo/addons/sale_product_rating_verified/static/description/index.html
odoo/addons/sale_product_rating_verified/static/description/rating_moderation_verified.png
odoo/addons/sale_product_rating_verified/tests/__init__.py
odoo/addons/sale_product_rating_verified/tests/test_verified.py
odoo/addons/sale_product_rating_verified/views/rating_view.xml
odoo14_addon_sale_product_rating_verified-14.0.1.0.2.dist-info/METADATA
odoo14_addon_sale_product_rating_verified-14.0.1.0.2.dist-info/WHEEL
odoo14_addon_sale_product_rating_verified-14.0.1.0.2.dist-info/top_level.txt
odoo14_addon_sale_product_rating_verified-14.0.1.0.2.dist-info/RECORD
